mlcast_datasets/__init__.py
mlcast_datasets/catalog/catalog.yml
mlcast_datasets/catalog/precipitation/catalog.yml
mlcast_datasets/tests/test_catalog.py
mlcast_datasets-0.1.1.dist-info/licenses/LICENSE-APACHE
mlcast_datasets-0.1.1.dist-info/licenses/LICENSE-BSD
mlcast_datasets-0.1.1.dist-info/METADATA
mlcast_datasets-0.1.1.dist-info/WHEEL
mlcast_datasets-0.1.1.dist-info/top_level.txt
mlcast_datasets-0.1.1.dist-info/RECORD
