Metadata-Version: 2.4
Name: mlcast-datasets
Version: 0.1.1
Summary: Intake catalog for datasets relevant for machine learning based nowcasting
Author-email: Leif Denby <lcd@dmi.dk>
License-Expression: Apache-2.0 OR BSD-3-Clause
Requires-Python: >=3.10
License-File: LICENSE-APACHE
License-File: LICENSE-BSD
Requires-Dist: intake>=2.0.8
Requires-Dist: intake-xarray>=2.0.0
Requires-Dist: ipykernel>=6.29.5
Requires-Dist: jinja2>=3.1.6
Requires-Dist: s3fs>=2025.0.0
Dynamic: license-file
